pquant/__init__.py
pquant/cli.py
pquant/method.py
pquant/schemas.py
pquant/template.py
pquant/strategy_demo/CrossCommodityArbitrage.py
pquant/strategy_demo/DualMovingAverageCrossover.py
pquant/strategy_demo/DualThrust.py
pquant/strategy_demo/GridTrading.py
pquant/strategy_demo/R-Breaker.py
pquant/strategy_demo/TurtleTrading.py
pquant/strategy_demo/indicator_my.py
pquant/strategy_demo/py.typed
pquant-0.1.2.dist-info/METADATA
pquant-0.1.2.dist-info/WHEEL
pquant-0.1.2.dist-info/entry_points.txt
pquant-0.1.2.dist-info/RECORD
