Metadata-Version: 2.4
Name: pquant
Version: 0.1.2
Summary: 口袋量化策略编写辅助工具。https://quant.gkoudai.com/
Author-email: yangchengye <chengye.yang@sojex.cn>
Requires-Python: >=3.9
